aryanbhatia_101703107_topsis/__init__.py
aryanbhatia_101703107_topsis/topsis.py
aryanbhatia_101703107_topsis-0.0.1.dist-info/LICENSE.txt
aryanbhatia_101703107_topsis-0.0.1.dist-info/METADATA
aryanbhatia_101703107_topsis-0.0.1.dist-info/WHEEL
aryanbhatia_101703107_topsis-0.0.1.dist-info/top_level.txt
aryanbhatia_101703107_topsis-0.0.1.dist-info/RECORD
