Metadata-Version: 2.1
Name: aryanbhatia-101703107-topsis
Version: 0.0.1
Summary: UNKNOWN
Home-page: UNKNOWN
Author: Aryan Bhatia
Author-email: abhatia_be17@thapar.edu
License: UNKNOWN
Platform: UNKNOWN
Classifier: Programming Language :: Python :: 3
Classifier: License :: OSI Approved :: MIT License
Classifier: Operating System :: OS Independent
Requires-Python: >=3.6
